<?xml version="1.0" encoding="UTF-8"?>
<features name="${project.artifactId}-${project.version}" xmlns="http://karaf.apache.org/xmlns/features/v1.0.0">

  <!-- <feature name="${project.artifactId}" description="${project.name}" version="${project.version}"> -->

    <!-- OH2 -->

    <feature name="openhab2-addon-sonos" description="" version="${project.version}">
        <bundle start-level="80">mvn:org.openhab.binding/org.openhab.binding.sonos/${project.version}</bundle>
    </feature>

    <feature name="openhab2-addon-max" description="" version="${project.version}">
        <bundle start-level="80">mvn:org.openhab.binding/org.openhab.binding.max/${project.version}</bundle>
    </feature>

    <feature name="openhab2-addon-astro" description="" version="${project.version}">
        <bundle start-level="80">mvn:org.openhab.binding/org.openhab.binding.astro/${project.version}</bundle>
    </feature>

    <feature name="openhab2-addon-autelis" description="" version="${project.version}">
        <bundle start-level="80">mvn:org.openhab.binding/org.openhab.binding.autelis/${project.version}</bundle>
    </feature>

    <feature name="openhab2-addon-avmfritz" description="" version="${project.version}">
        <bundle start-level="80">mvn:org.openhab.binding/org.openhab.binding.avmfritz/${project.version}</bundle>
    </feature>

    <feature name="openhab2-addon-sonos" description="" version="${project.version}">
        <bundle start-level="80">mvn:org.openhab.binding/org.openhab.binding.sonos/${project.version}</bundle>
    </feature>

    <feature name="openhab2-addon-freebox" description="" version="${project.version}">
        <bundle start-level="80">mvn:org.openhab.binding/org.openhab.binding.freebox/${project.version}</bundle>
    </feature>

    <feature name="openhab2-addon-hdanywhere" description="" version="${project.version}">
        <bundle start-level="80">mvn:org.openhab.binding/org.openhab.binding.hdanywhere/${project.version}</bundle>
    </feature>

    <feature name="openhab2-addon-ipp" description="" version="${project.version}">
        <bundle start-level="80">mvn:org.openhab.binding/org.openhab.binding.ipp/${project.version}</bundle>
    </feature>

    <feature name="openhab2-addon-keba" description="" version="${project.version}">
        <bundle start-level="80">mvn:org.openhab.binding/org.openhab.binding.keba/${project.version}</bundle>
    </feature>

    <feature name="openhab2-addon-sonos" description="" version="${project.version}">
        <bundle start-level="80">mvn:org.openhab.binding/org.openhab.binding.sonos/${project.version}</bundle>
    </feature>

    <feature name="openhab2-addon-network" description="" version="${project.version}">
        <bundle start-level="80">mvn:org.openhab.binding/org.openhab.binding.network/${project.version}</bundle>
    </feature>

    <feature name="openhab2-addon-pulseaudio" description="" version="${project.version}">
        <bundle start-level="80">mvn:org.openhab.binding/org.openhab.binding.pulseaudio/${project.version}</bundle>
    </feature>

    <feature name="openhab2-addon-pioneeravr" description="" version="${project.version}">
        <bundle start-level="80">mvn:org.openhab.binding/org.openhab.binding.pioneeravr/${project.version}</bundle>
    </feature>

    <feature name="openhab2-addon-squeezebox" description="" version="${project.version}">
        <bundle start-level="80">mvn:org.openhab.binding/org.openhab.binding.squeezebox/${project.version}</bundle>
    </feature>

    <feature name="openhab2-addon-tesla" description="" version="${project.version}">
        <bundle start-level="80">mvn:org.openhab.binding/org.openhab.binding.tesla/${project.version}</bundle>
    </feature>

    <feature name="openhab2-addon-vitotronic" description="" version="${project.version}">
        <bundle start-level="80">mvn:org.openhab.binding/org.openhab.binding.vitotronic/${project.version}</bundle>
    </feature>

    <feature name="openhab2-addon-myopenhab" description="" version="${project.version}">
        <bundle start-level="80">mvn:org.openhab.addons.io/org.openhab.io.myopenhab/${project.version}</bundle>
    </feature>

    <!-- ESH -->

    <feature name="openhab2-addon-yahooweather" description="" version="${project.version}">
        <bundle start-level="80">mvn:org.eclipse.smarthome.binding/org.eclipse.smarthome.binding.yahooweather/${esh.version}</bundle>
    </feature>

    <feature name="openhab2-addon-hue" description="" version="${project.version}">
        <bundle start-level="80">mvn:org.eclipse.smarthome.binding/org.eclipse.smarthome.binding.hue/${esh.version}</bundle>
    </feature>

    <feature name="openhab2-addon-wemo" description="" version="${project.version}">
        <bundle start-level="80">mvn:org.eclipse.smarthome.binding/org.eclipse.smarthome.binding.wemo/${esh.version}</bundle>
    </feature>

    <feature name="openhab2-addon-lifx" description="" version="${project.version}">
        <bundle start-level="80">mvn:org.eclipse.smarthome.binding/org.eclipse.smarthome.binding.lifx/${esh.version}</bundle>
    </feature>

    <!-- OH1 -->

    <feature name="openhab2-addon-anel" description="" version="${project.version}">
        <bundle start-level="80">mvn:org.openhab.binding/org.openhab.binding.anel/${oh1.version}</bundle>
    </feature>

    <feature name="openhab2-addon-denon" description="" version="${project.version}">
        <bundle start-level="80">mvn:org.openhab.binding/org.openhab.binding.denon/${oh1.version}</bundle>
        <configfile finalname="conf/services/denon.cfg" override="false">mvn:${project.groupId}/org.openhab.feature.addons.external/${project.version}/cfg/denon</configfile>
    </feature>

    <feature name="openhab2-addon-energenie" description="" version="${project.version}">
        <bundle start-level="80">mvn:org.openhab.binding/org.openhab.binding.energenie/${oh1.version}</bundle>
    </feature>

    <feature name="openhab2-addon-enocean" description="" version="${project.version}">
        <bundle start-level="80">mvn:org.openhab.binding/org.openhab.binding.enocean/${oh1.version}</bundle>
        <configfile finalname="conf/services/enocean.cfg" override="false">mvn:${project.groupId}/org.openhab.feature.addons.external/${project.version}/cfg/enocean</configfile>
    </feature>

    <feature name="openhab2-addon-epsonprojector" description="" version="${project.version}">
        <bundle start-level="80">mvn:org.openhab.binding/org.openhab.binding.epsonprojector/${oh1.version}</bundle>
        <configfile finalname="conf/services/epsonprojector.cfg" override="false">mvn:${project.groupId}/org.openhab.feature.addons.external/${project.version}/cfg/epsonprojector</configfile>
    </feature>

    <feature name="openhab2-addon-exec" description="" version="${project.version}">
        <bundle start-level="80">mvn:org.openhab.binding/org.openhab.binding.exec/${oh1.version}</bundle>
    </feature>

    <feature name="openhab2-addon-freeswitch" description="" version="${project.version}">
        <bundle start-level="80">mvn:org.openhab.binding/org.openhab.binding.freeswitch/${oh1.version}</bundle>
        <configfile finalname="conf/services/freeswitch.cfg" override="false">mvn:${project.groupId}/org.openhab.feature.addons.external/${project.version}/cfg/freeswitch</configfile>
    </feature>

    <feature name="openhab2-addon-fs20" description="" version="${project.version}">
        <bundle start-level="80">mvn:org.openhab.binding/org.openhab.binding.fs20/${oh1.version}</bundle>
    </feature>

    <feature name="openhab2-addon-heatmiser" description="" version="${project.version}">
        <bundle start-level="80">mvn:org.openhab.binding/org.openhab.binding.heatmiser/${oh1.version}</bundle>
        <configfile finalname="conf/services/heatmiser.cfg" override="false">mvn:${project.groupId}/org.openhab.feature.addons.external/${project.version}/cfg/heatmiser</configfile>
    </feature>

    <feature name="openhab2-addon-homematic" description="" version="${project.version}">
        <bundle start-level="80">mvn:org.openhab.binding/org.openhab.binding.homematic/${oh1.version}</bundle>
        <configfile finalname="conf/services/homematic.cfg" override="false">mvn:${project.groupId}/org.openhab.feature.addons.external/${project.version}/cfg/homematic</configfile>
    </feature>

    <feature name="openhab2-addon-http" description="" version="${project.version}">
        <bundle start-level="80">mvn:org.openhab.binding/org.openhab.binding.http/${oh1.version}</bundle>
        <configfile finalname="conf/services/http.cfg" override="false">mvn:${project.groupId}/org.openhab.feature.addons.external/${project.version}/cfg/http</configfile>
    </feature>

    <feature name="openhab2-addon-ihc" description="" version="${project.version}">
        <bundle start-level="80">mvn:org.openhab.binding/org.openhab.binding.ihc/${oh1.version}</bundle>
        <configfile finalname="conf/services/ihc.cfg" override="false">mvn:${project.groupId}/org.openhab.feature.addons.external/${project.version}/cfg/ihc</configfile>
    </feature>

    <feature name="openhab2-addon-insteonplm" description="" version="${project.version}">
        <bundle start-level="80">mvn:org.openhab.binding/org.openhab.binding.insteonplm/${oh1.version}</bundle>
        <configfile finalname="conf/services/insteonplm.cfg" override="false">mvn:${project.groupId}/org.openhab.feature.addons.external/${project.version}/cfg/insteonplm</configfile>
    </feature>

    <feature name="openhab2-addon-knx" description="" version="${project.version}">
        <bundle start-level="80">mvn:org.openhab.binding/org.openhab.binding.knx/${oh1.version}</bundle>
        <configfile finalname="conf/services/knx.cfg" override="false">mvn:${project.groupId}/org.openhab.feature.addons.external/${project.version}/cfg/knx</configfile>
    </feature>

    <feature name="openhab2-addon-milight" description="" version="${project.version}">
        <bundle start-level="80">mvn:org.openhab.binding/org.openhab.binding.milight/${oh1.version}</bundle>
        <configfile finalname="conf/services/milight.cfg" override="false">mvn:${project.groupId}/org.openhab.feature.addons.external/${project.version}/cfg/milight</configfile>
    </feature>

    <feature name="openhab2-addon-nibeheatpump" description="" version="${project.version}">
        <bundle start-level="80">mvn:org.openhab.binding/org.openhab.binding.nibeheatpump/${oh1.version}</bundle>
        <configfile finalname="conf/services/nibeheatpump.cfg" override="false">mvn:${project.groupId}/org.openhab.feature.addons.external/${project.version}/cfg/nibeheatpump</configfile>
    </feature>

    <feature name="openhab2-addon-ntp" description="" version="${project.version}">
        <bundle start-level="80">mvn:org.openhab.binding/org.openhab.binding.ntp/${oh1.version}</bundle>
        <configfile finalname="conf/services/ntp.cfg" override="false">mvn:${project.groupId}/org.openhab.feature.addons.external/${project.version}/cfg/ntp</configfile>
    </feature>

    <feature name="openhab2-addon-onkyo" description="" version="${project.version}">
        <bundle start-level="80">mvn:org.openhab.binding/org.openhab.binding.onkyo/${oh1.version}</bundle>
        <configfile finalname="conf/services/onkyo.cfg" override="false">mvn:${project.groupId}/org.openhab.feature.addons.external/${project.version}/cfg/onkyo</configfile>
    </feature>

    <feature name="openhab2-addon-openenergymonitor" description="" version="${project.version}">
        <bundle start-level="80">mvn:org.openhab.binding/org.openhab.binding.openenergymonitor/${oh1.version}</bundle>
        <configfile finalname="conf/services/openenergymonitor.cfg" override="false">mvn:${project.groupId}/org.openhab.feature.addons.external/${project.version}/cfg/openenergymonitor</configfile>
    </feature>

    <feature name="openhab2-addon-onewire" description="" version="${project.version}">
        <bundle start-level="80">mvn:org.openhab.binding/org.openhab.binding.onewire/${oh1.version}</bundle>
        <configfile finalname="conf/services/onewire.cfg" override="false">mvn:${project.groupId}/org.openhab.feature.addons.external/${project.version}/cfg/onewire</configfile>
    </feature>

    <feature name="openhab2-addon-owserver" description="" version="${project.version}">
        <bundle start-level="80">mvn:org.openhab.binding/org.openhab.binding.owserver/${oh1.version}</bundle>
        <configfile finalname="conf/services/owserver.cfg" override="false">mvn:${project.groupId}/org.openhab.feature.addons.external/${project.version}/cfg/owserver</configfile>
    </feature>

    <feature name="openhab2-addon-rfxcom" description="" version="${project.version}">
        <bundle start-level="80">mvn:org.openhab.binding/org.openhab.binding.rfxcom/${oh1.version}</bundle>
    </feature>

    <feature name="openhab2-addon-snmp" description="" version="${project.version}">
        <bundle start-level="80">mvn:org.openhab.binding/org.openhab.binding.snmp/${oh1.version}</bundle>
        <configfile finalname="conf/services/snmp.cfg" override="false">mvn:${project.groupId}/org.openhab.feature.addons.external/${project.version}/cfg/snmp</configfile>
    </feature>

    <feature name="openhab2-addon-systeminfo" description="" version="${project.version}">
        <bundle start-level="80">mvn:org.openhab.binding/org.openhab.binding.systeminfo/${oh1.version}</bundle>
        <configfile finalname="conf/services/systeminfo.cfg" override="false">mvn:${project.groupId}/org.openhab.feature.addons.external/${project.version}/cfg/systeminfo</configfile>
    </feature>

    <feature name="openhab2-addon-swegonventilation" description="" version="${project.version}">
        <bundle start-level="80">mvn:org.openhab.binding/org.openhab.binding.swegonventilation/${oh1.version}</bundle>
        <configfile finalname="conf/services/swegonventilation.cfg" override="false">mvn:${project.groupId}/org.openhab.feature.addons.external/${project.version}/cfg/swegonventilation</configfile>
    </feature>

    <feature name="openhab2-addon-tellstick" description="" version="${project.version}">
        <bundle start-level="80">mvn:org.openhab.binding/org.openhab.binding.tellstick/${oh1.version}</bundle>
    </feature>

    <feature name="openhab2-addon-tinkerforge" description="" version="${project.version}">
        <bundle start-level="80">mvn:org.openhab.binding/org.openhab.binding.tinkerforge/${oh1.version}</bundle>
        <configfile finalname="conf/services/tinkerforge.cfg" override="false">mvn:${project.groupId}/org.openhab.feature.addons.external/${project.version}/cfg/tinkerforge</configfile>
    </feature>

    <feature name="openhab2-addon-weather" description="" version="${project.version}">
        <bundle start-level="80">mvn:org.openhab.binding/org.openhab.binding.weather/${oh1.version}</bundle>
        <configfile finalname="conf/services/weather.cfg" override="false">mvn:${project.groupId}/org.openhab.feature.addons.external/${project.version}/cfg/weather</configfile>
    </feature>

    <feature name="openhab2-addon-zwave" description="" version="${project.version}">
        <bundle start-level="80">mvn:org.openhab.binding/org.openhab.binding.zwave/${oh1.version}</bundle>
        <configfile finalname="conf/services/zwave.cfg" override="false">mvn:${project.groupId}/org.openhab.feature.addons.external/${project.version}/cfg/zwave</configfile>
    </feature>

    <feature name="openhab2-addon-rrd4j" description="" version="${project.version}">
        <bundle start-level="80">mvn:org.openhab.persistence/org.openhab.persistence.rrd4j/${oh1.version}</bundle>
        <configfile finalname="conf/services/rrd4j.cfg" override="false">mvn:${project.groupId}/org.openhab.feature.addons.external/${project.version}/cfg/rrd4j</configfile>
    </feature>

    <feature name="openhab2-addon-mysql" description="" version="${project.version}">
        <bundle start-level="80">mvn:org.openhab.persistence/org.openhab.persistence.mysql/${oh1.version}</bundle>
        <configfile finalname="conf/services/mysql.cfg" override="false">mvn:${project.groupId}/org.openhab.feature.addons.external/${project.version}/cfg/mysql</configfile>
    </feature>

    <feature name="openhab2-addon-logging" description="" version="${project.version}">
        <bundle start-level="80">mvn:org.openhab.persistence/org.openhab.persistence.logging/${oh1.version}</bundle>
        <configfile finalname="conf/services/logging.cfg" override="false">mvn:${project.groupId}/org.openhab.feature.addons.external/${project.version}/cfg/logging</configfile>
    </feature>

    <feature name="openhab2-addon-jpa" description="" version="${project.version}">
        <bundle start-level="80">mvn:org.openhab.persistence/org.openhab.persistence.jpa/${oh1.version}</bundle>
        <configfile finalname="conf/services/jpa.cfg" override="false">mvn:${project.groupId}/org.openhab.feature.addons.external/${project.version}/cfg/jpa</configfile>
    </feature>

    <feature name="openhab2-addon-mail" description="" version="${project.version}">
        <bundle start-level="80">mvn:org.openhab.action/org.openhab.action.mail/${oh1.version}</bundle>
        <configfile finalname="conf/services/mail.cfg" override="false">mvn:${project.groupId}/org.openhab.feature.addons.external/${project.version}/cfg/mail</configfile>
    </feature>

    <feature name="openhab2-addon-pushover" description="" version="${project.version}">
        <bundle start-level="80">mvn:org.openhab.action/org.openhab.action.pushover/${oh1.version}</bundle>
        <configfile finalname="conf/services/pushover.cfg" override="false">mvn:${project.groupId}/org.openhab.feature.addons.external/${project.version}/cfg/pushover</configfile>
    </feature>

    <feature name="openhab2-addon-xbmc" description="" version="${project.version}">
        <bundle start-level="80">mvn:org.openhab.action/org.openhab.action.xbmc/${oh1.version}</bundle>
    </feature>

    <feature name="openhab2-addon-xmpp" description="" version="${project.version}">
        <bundle start-level="80">mvn:org.openhab.action/org.openhab.action.xmpp/${oh1.version}</bundle>
        <configfile finalname="conf/services/xmpp.cfg" override="false">mvn:${project.groupId}/org.openhab.feature.addons.external/${project.version}/cfg/xmpp</configfile>
    </feature>

    <feature name="openhab2-addon-marytts" description="" version="${project.version}">
        <bundle start-level="80">mvn:org.openhab.io/org.openhab.io.multimedia.tts.marytts/${oh1.version}</bundle>
        <configfile finalname="conf/services/marytts.cfg" override="false">mvn:${project.groupId}/org.openhab.feature.addons.external/${project.version}/cfg/marytts</configfile>
    </feature>

</features>
